README.md
setup.py
choclo_checker/__init__.py
choclo_checker.egg-info/PKG-INFO
choclo_checker.egg-info/SOURCES.txt
choclo_checker.egg-info/dependency_links.txt
choclo_checker.egg-info/requires.txt
choclo_checker.egg-info/top_level.txt
choclo_checker/api/__init__.py
choclo_checker/api/choclocheck_graphql.py
choclo_checker/api/choclocheck_rest.py
choclo_checker/api/choclocheck_soap.py
choclo_checker/db/__init__.py
choclo_checker/db/choclocheck_dynamodb.py
choclo_checker/db/choclocheck_elasticsearch.py
choclo_checker/db/choclocheck_influx.py
choclo_checker/db/choclocheck_mongodb.py
choclo_checker/db/choclocheck_mysql.py
choclo_checker/db/choclocheck_oracle.py
choclo_checker/db/choclocheck_postgres.py
choclo_checker/db/choclocheck_redis.py
choclo_checker/db/choclocheck_sql.py
choclo_checker/networking/__init__.py
choclo_checker/networking/choclocheck_ping.py