Metadata-Version: 1.0
Name: choclo-checker
Version: 1.0.1
Summary: Choclo checker
Home-page: https://jherranlarosa.com
Author: Julio César Herrán La Rosa
Author-email: jherranlarosa@gmail.com
License: UNKNOWN
Platform: UNKNOWN
